vegafusion-2.0.3.dist-info/METADATA
vegafusion-2.0.3.dist-info/WHEEL
vegafusion-2.0.3.dist-info/licenses/LICENSE
vegafusion/__init__.py
vegafusion/_vegafusion.abi3.so
vegafusion/jupyter/__init__.py
vegafusion/jupyter/js/index.js
vegafusion/local_tz.py
vegafusion/py.typed
vegafusion/runtime.py
vegafusion/transformer.py
vegafusion/utils.py
vegafusion-2.0.3.dist-info/RECORD
